zin/__init__.py
zin/__main__.py
zin/handler.py
zin/zin.py
zin-1.0.1.dist-info/entry_points.txt
zin-1.0.1.dist-info/LICENSE
zin-1.0.1.dist-info/METADATA
zin-1.0.1.dist-info/WHEEL
zin-1.0.1.dist-info/RECORD
