Metadata-Version: 2.1
Name: zin
Version: 1.0.1
Summary: zin is a lightweight command management tool that simplifies scripting and task automation.
Home-page: https://github.com/dishansa/zin
Keywords: tools,zin,automation,command management,script
Author: Dishan Sachin
Author-email: dishansachin99@gmail.com
Requires-Python: >=3.7
Classifier: Development Status :: 5 - Production/Stable
Classifier: License :: OSI Approved :: MIT License
Classifier: Operating System :: OS Independent
Classifier: Programming Language :: Python :: 3
Classifier: Programming Language :: Python :: 3.7
Classifier: Programming Language :: Python :: 3.8
Classifier: Programming Language :: Python :: 3.9
Classifier: Programming Language :: Python :: 3.10
Classifier: Programming Language :: Python :: 3.11
Classifier: Topic :: Utilities
Requires-Dist: pyyaml (>=6.0,<7.0)
Requires-Dist: rich (>=13.4.1,<14.0.0)
Project-URL: Repository, https://github.com/dishansa/zin
